abstractioutils/__init__.py
abstractioutils/clients/__init__.py
abstractioutils/clients/common_operations.py
abstractioutils/dto/__init__.py
abstractioutils/dto/cluster_dto.py
abstractioutils/exceptions/__init__.py
abstractioutils/exceptions/helpers_exception.py
abstractioutils/exceptions/http_exception.py
abstractioutils/exceptions/list_not_found_exception.py
abstractioutils/exceptions/aws/__init__.py
abstractioutils/exceptions/aws/dynamodb_exception.py
abstractioutils/exceptions/aws/sns_exception.py
abstractioutils/exceptions/aws/sqs_exception.py
abstractioutils/exceptions/aws/ssm_exception.py
abstractioutils/exceptions/gcp/__init__.py
abstractioutils/exceptions/gcp/cloud_run_exception.py
abstractioutils/exceptions/gcp/compute_engine_exception.py
abstractioutils/providers/__init__.py
abstractioutils/providers/aws/__init__.py
abstractioutils/providers/aws/base.py
abstractioutils/providers/aws/dynamodb.py
abstractioutils/providers/aws/sns.py
abstractioutils/providers/aws/sqs.py
abstractioutils/providers/aws/ssm.py
abstractioutils/providers/gcp/__init__.py
abstractioutils/providers/gcp/base.py
abstractioutils/providers/gcp/cloud_run.py
abstractioutils/providers/gcp/compute_engine.py
abstractioutils-1.0.6.dist-info/METADATA
abstractioutils-1.0.6.dist-info/WHEEL
abstractioutils-1.0.6.dist-info/top_level.txt
abstractioutils-1.0.6.dist-info/RECORD
