Metadata-Version: 2.1
Name: abstractioutils
Version: 1.0.6
Summary: Common packages used in Abstractio
Home-page: https://github.com/stefanocascavilla/abstractioutils
Author: Stefano Cascavilla
Author-email: cascavilla1@gmail.com
License: MIT
Platform: UNKNOWN
Classifier: License :: OSI Approved :: MIT License
Classifier: Programming Language :: Python :: 3
Classifier: Programming Language :: Python :: 3.7
Requires-Dist: boto3 (==1.16.63)
Requires-Dist: google-api-python-client (==1.8.0)
Requires-Dist: google-auth (==1.28.1)
Requires-Dist: oauth2client (==4.1.3)
Requires-Dist: pydantic (==1.8.1)
